morepipes.py
morepipes-1.0.4.dist-info/LICENSE
morepipes-1.0.4.dist-info/METADATA
morepipes-1.0.4.dist-info/WHEEL
morepipes-1.0.4.dist-info/top_level.txt
morepipes-1.0.4.dist-info/RECORD
