Metadata-Version: 2.1
Name: morepipes
Version: 1.0.4
Summary: Extended pipes for functional programming
License: MIT License
Project-URL: Homepage, https://github.com/tovicheung/morepipes
Classifier: License :: OSI Approved :: MIT License
Classifier: Programming Language :: Python
Classifier: Programming Language :: Python :: 3
Classifier: Intended Audience :: Developers
Classifier: Operating System :: OS Independent
Classifier: Topic :: Software Development
Classifier: Topic :: Software Development :: Libraries :: Python Modules
License-File: LICENSE
Requires-Dist: pipe >=2.0
